diff_reviewer/__init__.py
diff_reviewer/main.py
diff_reviewer/reviewer.py
hooks/pre-commit
diff_reviewer-0.1.1.dist-info/LICENSE
diff_reviewer-0.1.1.dist-info/METADATA
diff_reviewer-0.1.1.dist-info/WHEEL
diff_reviewer-0.1.1.dist-info/entry_points.txt
diff_reviewer-0.1.1.dist-info/top_level.txt
diff_reviewer-0.1.1.dist-info/RECORD
