Metadata-Version: 2.1
Name: diff-reviewer
Version: 0.1.1
Summary: AI-based local code diff reviewer that runs on every git commit.
Home-page: https://github.com/ChargedMonk/DiffReviewer
Author: Vatsalya Bajpai
Author-email: vatsalyabajpai03@example.com
Classifier: Programming Language :: Python :: 3
Classifier: License :: OSI Approved :: MIT License
Classifier: Operating System :: OS Independent
Requires-Python: >=3.8
License-File: LICENSE
Requires-Dist: llama-cpp-python ==0.3.8
Requires-Dist: gdown ==5.2.0
